qtree/__init__.py
qtree/einsum.py
qtree/logger_setup.py
qtree/np_framework.py
qtree/operators.py
qtree/optimizer.py
qtree/simulator.py
qtree/system_defs.py
qtree/tf_framework.py
qtree/utils.py
qtree/graph_model/__init__.py
qtree/graph_model/base.py
qtree/graph_model/clique_trees.py
qtree/graph_model/exporters.py
qtree/graph_model/generators.py
qtree/graph_model/importers.py
qtree/graph_model/pace2017_solver_api.py
qtree/graph_model/peo_calculation.py
qtree/graph_model/peo_reordering.py
qtree/graph_model/quickbb_api.py
qtree/graph_model/splitters.py
qtree-0.1.dist-info/LICENSE
qtree-0.1.dist-info/METADATA
qtree-0.1.dist-info/WHEEL
qtree-0.1.dist-info/top_level.txt
qtree-0.1.dist-info/RECORD
